[
  {
    "type": "visual",
    "layout": "center",
    "media": "assets/model.glb",
    "mediaType": "model",
    "caption": "Interactive 3D model viewer (GLB). Use mouse/touch to rotate and pinch to zoom.",
    "height": 700,
    "mediaScale": 1.0,
    "mediaBoxW": 1100,
    "mediaBoxH": 700,
    "subtype": "model"
  },
  {
    "type": "visual",
    "layout": "center",
    "media": "assets/grey_glacier_1980.jpeg",
    "media2": "assets/grey_glacier_google.jpeg",
    "mediaType": "image",
    "media2Type": "image",
    "caption": "Grey Glacier (Patagonia) comparison: 1980 vs 2022.",
    "height": 700,
    "mediaScale": 1.0,
    "mediaBoxW": 700,
    "mediaBoxH": 700,
    "subtype": "compare"
  },
  {
    "title": "Advances in Historical Aerial Image Analysis: Boosting SfM Pipelines with Learned Models",
    "excerpt": "For 2025 EGU conference we did inital tests with learned feature extractors/matchers (e.g., SuperPoint, SuperGlue, LoFTR) to evaluate SfM processes on scanned historical aerial photos (using only open-source solutions). For the study 1980 Southern Patagonian imagery were used. We compare model combos with reprojection and co-registration metrics.",
    "media": "assets/post_4_ani.mp4",
    "mediaType": "video",
    "date": "2025-10-05",
    "href": "articles/EGU25_Grey_Glacier.md",
    "height": 550,
    "layout": "media-left",
    "mediaBoxW": 550,
    "mediaBoxH": 550,
    "mobileMaxVH": 50,
    "presentation": "assets/posters/EGU_25_presentation.pdf",
    "conferenceAbstract": "https://meetingorganizer.copernicus.org/EGU25/EGU25-17688.html"
  },
  {
    "type": "visual",
    "layout": "center",
    "media": "assets/grey_glacier_long.png",
    "mediaType": "image",
    "caption": "Reculus Glacier (Patagonia) 1980.",
    "height": 330,
    "mediaScale": 1.0,
    "mediaBoxW": 1100,
    "mediaBoxH": 330
  },
  {
    "type": "visual",
    "layout": "left",
    "media": "assets/ani_1.mp4",
    "mediaType": "video",
    "caption": "A short looping animation on the left, caption on the right.",
    "height": 420,
    "mediaScale": 0.55,
    "mediaBoxW": 360,
    "mediaBoxH": 360
  },
  {
    "type": "visual",
    "layout": "right",
    "media": "assets/sample-1.png",
    "mediaType": "image",
    "caption": "Media on the right, caption on the left.",
    "height": 420,
    "mediaScale": 0.6,
    "mediaBoxW": 380,
    "mediaBoxH": 260
  },
  {
    "type": "visual",
    "layout": "two",
    "media": "assets/post_3_sn_1965.jpeg",
    "mediaType": "image",
    "media2": "assets/post_3_sn_1975.jpeg",
    "media2Type": "image",
    "caption": "CORONA imagery over Leisnig (Saxony) 1965 & 1975.",
    "height": 600,
    "mediaScale": 0.9,
    "mediaBoxW": 600,
    "mediaBoxH": 600
  },
  {
    "title": "Harvesting historical spy imagery by evaluating deep learning models for land cover mapping in Saxony",
    "excerpt": "Processing land cover maps from CORONA spy imagery — part of my Master’s thesis project.",
    "media": "assets/post_1_header_corona.jpg",
    "mediaType": "image",
    "date": "2025-10-05",
    "href": "articles/harvesting-corona.md",
    "height": 600,
    "layout": "media-left",
    "mediaBoxW": 600,
    "mediaBoxH": 600,
    "mobileMaxVH": 50,
    "poster": "assets/posters/harvesting-corona-poster.pdf",
    "viewer": "https://geoviewer.sachsen.de/mapviewer/resources/apps/hilubi/index.html?lang=en",
    "projectReport": "https://publikationen.sachsen.de/bdb/artikel/42436"
  },
  {
    "type": "visual",
    "layout": "center",
    "media": "assets/post_3_dd_1975.png",
    "mediaType": "image",
    "caption": "CORONA Imagery over Dresden 1975.",
    "height": 380,
    "mediaScale": 1,
    "mediaBoxW": 1100,
    "mediaBoxH": 380
  },
  {
    "title": "Telegram Network Analysis of the Saxon right-wing party Free Saxony",
    "excerpt": "For a Friends semester project in Political Science I collected a database of Telegram channels in the sphere of the right wing partie Freie Sachsen",
    "media": "assets/post_2_header_tele.jpeg",
    "mediaType": "image",
    "date": "2025-10-05",
    "href": "articles/network_anlysis.md",
    "height": 600,
    "layout": "media-left",
    "mediaBoxW": 1100,
    "mediaBoxH": 600,
    "mobileMaxVH": 50
  }
]